tiger_and_dragon/__init__.py
tiger_and_dragon/main.py
tiger_and_dragon/test_main.py
tiger_and_dragon-0.1.1.dist-info/licenses/LICENSE
tiger_and_dragon-0.1.1.dist-info/METADATA
tiger_and_dragon-0.1.1.dist-info/WHEEL
tiger_and_dragon-0.1.1.dist-info/entry_points.txt
tiger_and_dragon-0.1.1.dist-info/top_level.txt
tiger_and_dragon-0.1.1.dist-info/RECORD
