Metadata-Version: 2.4
Name: tiger-and-dragon
Version: 0.1.1
Summary: A Python script to calculate and display the Heavenly Stem (Jikkan) and Earthly Branch (Eto/Junishi) for a given date.
License: MIT License
Classifier: Programming Language :: Python :: 3
Classifier: Programming Language :: Python :: 3.12
Classifier: Operating System :: OS Independent
Classifier: Topic :: Utilities
Requires-Python: >=3.12
License-File: LICENSE
Dynamic: license-file
